{"Corentin": {"solde_initial": 2000.0, "revenus": [{"montant": 25.0, "date": "20/05/2024", "commentaire": "Cantine"}, {"montant": 100.0, "date": "21/05/2024", "commentaire": "AGE"}, {"montant": 234.0, "date": "22/05/2024", "commentaire": "Autre"}], "depenses": [{"montant": 10.0, "date": "23/05/2024", "commentaire": "Mcdo"}, {"montant": 100.0, "date": "05/02/2024", "commentaire": "Tennis"}, {"montant": 300.0, "date": "26/02/2024", "commentaire": "YTB"}, {"montant": 100.0, "date": "30/04/2023", "commentaire": "Boutique"}]}, "Louis": {"solde_initial": 1000.0, "revenus": [{"montant": 250.0, "date": "20/05/2024", "commentaire": "Cantine"}, {"montant": 250.0, "date": "22/05/2024", "commentaire": "Moi"}], "depenses": [{"montant": 500.0, "date": "23/05/2024", "commentaire": "Mcdo"}]}, "Dorian": {"solde_initial": 0, "revenus": [], "depenses": []}, "Amaury": {"solde_initial": 200.0, "revenus": [], "depenses": []}}